README.txt
setup.py
txOneDrive.egg-info/PKG-INFO
txOneDrive.egg-info/SOURCES.txt
txOneDrive.egg-info/dependency_links.txt
txOneDrive.egg-info/requires.txt
txOneDrive.egg-info/top_level.txt
txonedrive/__init__.py
txonedrive/api_v5.py