Metadata-Version: 1.1
Name: txOneDrive
Version: 14.04.0
Summary: Twisted-based async interface for Microsoft LiveConnect OneDrive REST API v5.0
Home-page: https://github.com/mk-fg/txonedrive
Author: Mike Kazantsev
Author-email: mk.fraggod@gmail.com
License: WTFPL
Keywords: onedrive,skydrive,twisted,async,api,oauth2,rest,microsoft,cloud,live,liveconnect,json,storage,storage provider,file hosting
Platform: UNKNOWN
Classifier: Development Status :: 4 - Beta
Classifier: Environment :: Plugins
Classifier: Framework :: Twisted
Classifier: Intended Audience :: Developers
Classifier: Intended Audience :: Information Technology
Classifier: License :: OSI Approved
Classifier: Operating System :: OS Independent
Classifier: Programming Language :: Python
Classifier: Programming Language :: Python :: 2.7
Classifier: Programming Language :: Python :: 2 :: Only
Classifier: Topic :: Internet
Classifier: Topic :: System :: Archiving
Classifier: Topic :: System :: Filesystems
